blizzardapi3/__init__.py
blizzardapi3/blizzard_api.py
blizzardapi3/blizzard_api.pyi
blizzardapi3/types.py
blizzardapi3/api/__init__.py
blizzardapi3/api/d3.py
blizzardapi3/api/d3.pyi
blizzardapi3/api/hs.py
blizzardapi3/api/hs.pyi
blizzardapi3/api/sc2.py
blizzardapi3/api/sc2.pyi
blizzardapi3/api/wow.py
blizzardapi3/api/wow.pyi
blizzardapi3/config/endpoints/d3_community.yaml
blizzardapi3/config/endpoints/d3_game_data.yaml
blizzardapi3/config/endpoints/hs_game_data.yaml
blizzardapi3/config/endpoints/sc2_community.yaml
blizzardapi3/config/endpoints/sc2_game_data.yaml
blizzardapi3/config/endpoints/wow_game_data.yaml
blizzardapi3/config/endpoints/wow_profile.yaml
blizzardapi3/core/__init__.py
blizzardapi3/core/auth.py
blizzardapi3/core/client.py
blizzardapi3/core/context.py
blizzardapi3/core/executor.py
blizzardapi3/core/factory.py
blizzardapi3/core/registry.py
blizzardapi3/exceptions/__init__.py
blizzardapi3/exceptions/auth.py
blizzardapi3/exceptions/base.py
blizzardapi3/exceptions/request.py
blizzardapi3/exceptions/validation.py
blizzardapi3-3.0.3.dist-info/METADATA
blizzardapi3-3.0.3.dist-info/WHEEL
blizzardapi3-3.0.3.dist-info/top_level.txt
blizzardapi3-3.0.3.dist-info/RECORD
