Metadata-Version: 2.4
Name: blizzardapi3
Version: 3.0.3
Summary: A modern, config-driven Python wrapper for the Blizzard API with async support
Author-email: lostcol0ny <c098os0k@4wrd.cc>
License-Expression: MIT
Project-URL: Homepage, https://github.com/lostcol0ny/blizzardapi3
Project-URL: Documentation, https://github.com/lostcol0ny/blizzardapi3#readme
Project-URL: Repository, https://github.com/lostcol0ny/blizzardapi3
Project-URL: Issues, https://github.com/lostcol0ny/blizzardapi3/issues
Classifier: Programming Language :: Python :: 3
Classifier: Programming Language :: Python :: 3.11
Classifier: Programming Language :: Python :: 3.12
Classifier: Programming Language :: Python :: 3.13
Classifier: Operating System :: OS Independent
Classifier: Development Status :: 4 - Beta
Classifier: Intended Audience :: Developers
Classifier: Topic :: Software Development :: Libraries :: Python Modules
Requires-Python: >=3.11
Requires-Dist: requests<3.0.0,>=2.32.3
Requires-Dist: aiohttp<4.0.0,>=3.12.12
Requires-Dist: pydantic<3.0.0,>=2.11.6
Requires-Dist: pyyaml<7.0.0,>=6.0
Provides-Extra: dev
Requires-Dist: pytest<10.0.0,>=8.2.2; extra == "dev"
Requires-Dist: pytest-mock<4.0.0,>=3.14.0; extra == "dev"
Requires-Dist: pytest-asyncio<2.0.0,>=0.23.5; extra == "dev"
Requires-Dist: black<26.0.0,>=24.4.2; extra == "dev"
Requires-Dist: ruff<1.0.0,>=0.3.0; extra == "dev"
Provides-Extra: examples
Requires-Dist: python-dotenv<2.0.0,>=1.0.0; extra == "examples"
